lossesofrussia/__init__.py
Lossesofrussia-1.0.dist-info/METADATA
Lossesofrussia-1.0.dist-info/WHEEL
Lossesofrussia-1.0.dist-info/top_level.txt
Lossesofrussia-1.0.dist-info/RECORD
